behi_admin-0.2.1.dist-info/licenses/LICENSE
modern_django_admin/__init__.py
modern_django_admin/admin.py
modern_django_admin/apps.py
modern_django_admin/conf.py
modern_django_admin/context_processors.py
modern_django_admin/signals.py
modern_django_admin/urls.py
modern_django_admin/widgets.py
modern_django_admin/locale/ar/LC_MESSAGES/django.po
modern_django_admin/locale/de/LC_MESSAGES/django.po
modern_django_admin/locale/en/LC_MESSAGES/django.po
modern_django_admin/locale/es/LC_MESSAGES/django.po
modern_django_admin/locale/fa/LC_MESSAGES/django.po
modern_django_admin/locale/it/LC_MESSAGES/django.po
modern_django_admin/static/modern_admin/css/base.css
modern_django_admin/static/modern_admin/css/change_form.css
modern_django_admin/static/modern_admin/css/change_list.css
modern_django_admin/static/modern_admin/css/components.css
modern_django_admin/static/modern_admin/css/dark.css
modern_django_admin/static/modern_admin/css/dashboard.css
modern_django_admin/static/modern_admin/css/login.css
modern_django_admin/static/modern_admin/css/rtl.css
modern_django_admin/static/modern_admin/css/tokens.css
modern_django_admin/static/modern_admin/js/base.js
modern_django_admin/static/modern_admin/js/dark-mode.js
modern_django_admin/templates/admin/app_index.html
modern_django_admin/templates/admin/base.html
modern_django_admin/templates/admin/base_site.html
modern_django_admin/templates/admin/change_form.html
modern_django_admin/templates/admin/change_list.html
modern_django_admin/templates/admin/delete_confirmation.html
modern_django_admin/templates/admin/delete_selected_confirmation.html
modern_django_admin/templates/admin/filter.html
modern_django_admin/templates/admin/index.html
modern_django_admin/templates/admin/object_history.html
modern_django_admin/templates/admin/includes/actions.html
modern_django_admin/templates/admin/includes/fieldset.html
modern_django_admin/templates/admin/includes/filter.html
modern_django_admin/templates/admin/includes/header.html
modern_django_admin/templates/admin/includes/messages.html
behi_admin-0.2.1.dist-info/METADATA
behi_admin-0.2.1.dist-info/WHEEL
behi_admin-0.2.1.dist-info/top_level.txt
behi_admin-0.2.1.dist-info/RECORD
