Metadata-Version: 2.4
Name: behi-admin
Version: 0.2.1
Summary: A modern, responsive, RTL/LTR-ready Django Admin Panel with enhanced UI/UX
Author: Behi Admin Team
License: MIT
Project-URL: Homepage, https://github.com/yourusername/behi-admin
Project-URL: Documentation, https://github.com/yourusername/behi-admin#readme
Project-URL: Repository, https://github.com/yourusername/behi-admin
Project-URL: Issues, https://github.com/yourusername/behi-admin/issues
Project-URL: Demo, https://yourusername.github.io/behi-admin/
Keywords: django,admin,ui,ux,rtl,ltr,modern,responsive
Classifier: Development Status :: 4 - Beta
Classifier: Environment :: Web Environment
Classifier: Framework :: Django
Classifier: Framework :: Django :: 3.2
Classifier: Framework :: Django :: 4.2
Classifier: Framework :: Django :: 5.0
Classifier: Intended Audience :: Developers
Classifier: License :: OSI Approved :: MIT License
Classifier: Operating System :: OS Independent
Classifier: Programming Language :: Python
Classifier: Programming Language :: Python :: 3
Classifier: Programming Language :: Python :: 3.9
Classifier: Programming Language :: Python :: 3.10
Classifier: Programming Language :: Python :: 3.11
Classifier: Programming Language :: Python :: 3.12
Classifier: Topic :: Internet :: WWW/HTTP
Classifier: Topic :: Internet :: WWW/HTTP :: Dynamic Content
Requires-Python: >=3.9
License-File: LICENSE
Requires-Dist: Django<6.0,>=3.2
Provides-Extra: dev
Requires-Dist: pytest>=7.0; extra == "dev"
Requires-Dist: pytest-django>=4.5.0; extra == "dev"
Requires-Dist: ruff>=0.1.0; extra == "dev"
Requires-Dist: black>=23.0.0; extra == "dev"
Requires-Dist: mypy>=1.0.0; extra == "dev"
Requires-Dist: django-stubs>=4.0.0; extra == "dev"
Dynamic: license-file
